voicent/__init__.py
voicent/voicent.py
Voicent_Python-1.0.dist-info/METADATA
Voicent_Python-1.0.dist-info/WHEEL
Voicent_Python-1.0.dist-info/top_level.txt
Voicent_Python-1.0.dist-info/RECORD
