Metadata-Version: 2.1
Name: Voicent-Python
Version: 1.0
Summary: Voicent Python Library
Home-page: https://github.com/ursais/Voicent
Author: Voicent
Author-email: support@voicent.com
License: UNKNOWN
Keywords: voicent-python
Platform: UNKNOWN
Classifier: Development Status :: 5 - Production/Stable
Classifier: Intended Audience :: Developers
Classifier: License :: OSI Approved :: GNU Affero General Public License v3 or later (AGPLv3+)
Classifier: Operating System :: OS Independent
Classifier: Programming Language :: Python :: 3
Classifier: Topic :: Software Development :: Libraries :: Python Modules
Classifier: Topic :: Communications :: Telephony
Requires-Dist: requests (>=2.20.0)
Requires-Dist: requests (>=2.20.0) ; python_version>="3.0"
